jira_html_report/__init__.py
jira_html_report/data.py
jira_html_report/report.py
jira_html_report/html_templates/chart_template.j2
jira_html_report/html_templates/report_template.j2
jira_html_report/html_templates/table_template.j2
jira_html_report-0.5.0.dist-info/METADATA
jira_html_report-0.5.0.dist-info/WHEEL
jira_html_report-0.5.0.dist-info/top_level.txt
jira_html_report-0.5.0.dist-info/RECORD
