Metadata-Version: 2.2
Name: jira-html-report
Version: 0.5.0
Summary: Generating Jira report to see issue trends.
Author-email: freeyssu <freeyssu@gmail.com>
License: MIT
Project-URL: Homepage, https://github.com/freeyssu/jira_html_report
Project-URL: Repository, https://github.com/freeyssu/jira_html_report
Keywords: atlassian,jira,report
Requires-Python: >=3.8
Requires-Dist: jira
Requires-Dist: pandas
Requires-Dist: plotly
Requires-Dist: jinja2
